<Gesture Name="arrow03" User="1" Number="3" NumPts="142" Milliseconds="1561.040">
<Point X="113" Y="191" T="1645050243.000"/>
<Point X="129" Y="179" T="1645050243.889"/>
<Point X="133" Y="177" T="1645050243.896"/>
<Point X="137" Y="174" T="1645050243.896"/>
<Point X="140" Y="172" T="1645050243.896"/>
<Point X="144" Y="170" T="1645050243.904"/>
<Point X="148" Y="168" T="1645050243.905"/>
<Point X="152" Y="165" T="1645050243.905"/>
<Point X="156" Y="162" T="1645050243.920"/>
<Point X="161" Y="160" T="1645050243.920"/>
<Point X="165" Y="157" T="1645050243.920"/>
<Point X="169" Y="154" T="1645050243.920"/>
<Point X="173" Y="151" T="1645050243.934"/>
<Point X="178" Y="149" T="1645050243.934"/>
<Point X="187" Y="143" T="1645050243.941"/>
<Point X="192" Y="140" T="1645050243.949"/>
<Point X="197" Y="137" T="1645050243.949"/>
<Point X="202" Y="134" T="1645050243.956"/>
<Point X="207" Y="131" T="1645050243.956"/>
<Point X="212" Y="128" T="1645050243.964"/>
<Point X="217" Y="125" T="1645050243.964"/>
<Point X="228" Y="119" T="1645050243.970"/>
<Point X="234" Y="115" T="1645050243.980"/>
<Point X="239" Y="112" T="1645050243.982"/>
<Point X="244" Y="109" T="1645050243.982"/>
<Point X="248" Y="107" T="1645050243.982"/>
<Point X="253" Y="104" T="1645050243.994"/>
<Point X="258" Y="101" T="1645050243.994"/>
<Point X="263" Y="99" T="1645050243.994"/>
<Point X="268" Y="96" T="1645050243.994"/>
<Point X="273" Y="94" T="1645050244.010"/>
<Point X="277" Y="92" T="1645050244.012"/>
<Point X="285" Y="87" T="1645050244.012"/>
<Point X="289" Y="86" T="1645050244.023"/>
<Point X="293" Y="84" T="1645050244.023"/>
<Point X="296" Y="82" T="1645050244.032"/>
<Point X="299" Y="81" T="1645050244.032"/>
<Point X="302" Y="80" T="1645050244.038"/>
<Point X="305" Y="78" T="1645050244.038"/>
<Point X="309" Y="77" T="1645050244.047"/>
<Point X="311" Y="76" T="1645050244.054"/>
<Point X="312" Y="75" T="1645050244.054"/>
<Point X="314" Y="75" T="1645050244.061"/>
<Point X="314" Y="74" T="1645050244.063"/>
<Point X="315" Y="74" T="1645050244.070"/>
<Point X="315" Y="73" T="1645050244.070"/>
<Point X="314" Y="73" T="1645050244.085"/>
<Point X="313" Y="73" T="1645050244.091"/>
<Point X="312" Y="73" T="1645050244.091"/>
<Point X="311" Y="73" T="1645050244.098"/>
<Point X="310" Y="73" T="1645050244.098"/>
<Point X="307" Y="73" T="1645050244.107"/>
<Point X="306" Y="73" T="1645050244.107"/>
<Point X="304" Y="73" T="1645050244.107"/>
<Point X="302" Y="74" T="1645050244.107"/>
<Point X="299" Y="74" T="1645050244.122"/>
<Point X="297" Y="74" T="1645050244.128"/>
<Point X="294" Y="75" T="1645050244.130"/>
<Point X="288" Y="76" T="1645050244.136"/>
<Point X="285" Y="76" T="1645050244.136"/>
<Point X="282" Y="77" T="1645050244.136"/>
<Point X="276" Y="78" T="1645050244.152"/>
<Point X="272" Y="79" T="1645050244.159"/>
<Point X="269" Y="79" T="1645050244.159"/>
<Point X="262" Y="81" T="1645050244.159"/>
<Point X="258" Y="81" T="1645050244.175"/>
<Point X="255" Y="82" T="1645050244.177"/>
<Point X="252" Y="83" T="1645050244.181"/>
<Point X="249" Y="84" T="1645050244.181"/>
<Point X="245" Y="84" T="1645050244.181"/>
<Point X="242" Y="85" T="1645050244.181"/>
<Point X="239" Y="86" T="1645050244.196"/>
<Point X="236" Y="86" T="1645050244.196"/>
<Point X="234" Y="87" T="1645050244.203"/>
<Point X="231" Y="88" T="1645050244.206"/>
<Point X="227" Y="89" T="1645050244.211"/>
<Point X="223" Y="89" T="1645050244.218"/>
<Point X="220" Y="90" T="1645050244.226"/>
<Point X="219" Y="91" T="1645050244.230"/>
<Point X="218" Y="91" T="1645050244.230"/>
<Point X="219" Y="91" T="1645050244.249"/>
<Point X="220" Y="91" T="1645050244.249"/>
<Point X="221" Y="90" T="1645050244.265"/>
<Point X="223" Y="90" T="1645050244.265"/>
<Point X="225" Y="90" T="1645050244.265"/>
<Point X="226" Y="89" T="1645050244.265"/>
<Point X="228" Y="89" T="1645050244.265"/>
<Point X="231" Y="88" T="1645050244.281"/>
<Point X="233" Y="87" T="1645050244.286"/>
<Point X="236" Y="87" T="1645050244.286"/>
<Point X="239" Y="86" T="1645050244.294"/>
<Point X="242" Y="85" T="1645050244.294"/>
<Point X="249" Y="83" T="1645050244.301"/>
<Point X="253" Y="82" T="1645050244.310"/>
<Point X="257" Y="81" T="1645050244.310"/>
<Point X="265" Y="79" T="1645050244.310"/>
<Point X="269" Y="78" T="1645050244.324"/>
<Point X="272" Y="77" T="1645050244.324"/>
<Point X="276" Y="76" T="1645050244.331"/>
<Point X="280" Y="74" T="1645050244.331"/>
<Point X="285" Y="73" T="1645050244.339"/>
<Point X="289" Y="72" T="1645050244.339"/>
<Point X="294" Y="71" T="1645050244.347"/>
<Point X="298" Y="70" T="1645050244.347"/>
<Point X="302" Y="68" T="1645050244.354"/>
<Point X="306" Y="67" T="1645050244.357"/>
<Point X="314" Y="66" T="1645050244.361"/>
<Point X="318" Y="65" T="1645050244.369"/>
<Point X="322" Y="64" T="1645050244.369"/>
<Point X="329" Y="63" T="1645050244.369"/>
<Point X="332" Y="63" T="1645050244.386"/>
<Point X="335" Y="63" T="1645050244.386"/>
<Point X="340" Y="63" T="1645050244.386"/>
<Point X="344" Y="63" T="1645050244.398"/>
<Point X="347" Y="64" T="1645050244.407"/>
<Point X="350" Y="67" T="1645050244.422"/>
<Point X="350" Y="69" T="1645050244.430"/>
<Point X="350" Y="70" T="1645050244.430"/>
<Point X="350" Y="73" T="1645050244.430"/>
<Point X="349" Y="75" T="1645050244.446"/>
<Point X="348" Y="76" T="1645050244.446"/>
<Point X="346" Y="80" T="1645050244.446"/>
<Point X="344" Y="82" T="1645050244.446"/>
<Point X="342" Y="85" T="1645050244.462"/>
<Point X="340" Y="88" T="1645050244.462"/>
<Point X="337" Y="91" T="1645050244.462"/>
<Point X="334" Y="93" T="1645050244.475"/>
<Point X="331" Y="97" T="1645050244.477"/>
<Point X="326" Y="102" T="1645050244.477"/>
<Point X="323" Y="105" T="1645050244.490"/>
<Point X="320" Y="109" T="1645050244.490"/>
<Point X="312" Y="117" T="1645050244.497"/>
<Point X="308" Y="121" T="1645050244.505"/>
<Point X="305" Y="125" T="1645050244.505"/>
<Point X="297" Y="133" T="1645050244.505"/>
<Point X="294" Y="137" T="1645050244.520"/>
<Point X="291" Y="141" T="1645050244.520"/>
<Point X="288" Y="145" T="1645050244.539"/>
<Point X="280" Y="154" T="1645050244.539"/>
<Point X="279" Y="157" T="1645050244.555"/>
<Point X="274" Y="165" T="1645050244.555"/>
<Point X="273" Y="167" T="1645050244.561"/>
</Gesture>
