<Gesture Name="arrow05" User="0" Number="5" NumPts="200" Milliseconds="1678.870">
<Point X="169" Y="202" T="1645027075.000"/>
<Point X="185" Y="192" T="1645027075.551"/>
<Point X="188" Y="190" T="1645027075.551"/>
<Point X="191" Y="189" T="1645027075.551"/>
<Point X="195" Y="187" T="1645027075.566"/>
<Point X="198" Y="186" T="1645027075.566"/>
<Point X="202" Y="184" T="1645027075.566"/>
<Point X="207" Y="182" T="1645027075.566"/>
<Point X="212" Y="180" T="1645027075.566"/>
<Point X="217" Y="178" T="1645027075.582"/>
<Point X="222" Y="176" T="1645027075.582"/>
<Point X="227" Y="174" T="1645027075.582"/>
<Point X="232" Y="172" T="1645027075.582"/>
<Point X="236" Y="170" T="1645027075.582"/>
<Point X="241" Y="168" T="1645027075.604"/>
<Point X="245" Y="166" T="1645027075.604"/>
<Point X="250" Y="164" T="1645027075.609"/>
<Point X="255" Y="161" T="1645027075.609"/>
<Point X="260" Y="159" T="1645027075.609"/>
<Point X="266" Y="157" T="1645027075.618"/>
<Point X="271" Y="155" T="1645027075.625"/>
<Point X="276" Y="152" T="1645027075.628"/>
<Point X="286" Y="148" T="1645027075.628"/>
<Point X="289" Y="146" T="1645027075.628"/>
<Point X="292" Y="145" T="1645027075.628"/>
<Point X="295" Y="143" T="1645027075.646"/>
<Point X="299" Y="142" T="1645027075.646"/>
<Point X="304" Y="140" T="1645027075.646"/>
<Point X="308" Y="138" T="1645027075.646"/>
<Point X="312" Y="136" T="1645027075.663"/>
<Point X="316" Y="135" T="1645027075.663"/>
<Point X="320" Y="133" T="1645027075.663"/>
<Point X="323" Y="132" T="1645027075.663"/>
<Point X="326" Y="131" T="1645027075.676"/>
<Point X="329" Y="130" T="1645027075.676"/>
<Point X="331" Y="129" T="1645027075.687"/>
<Point X="333" Y="128" T="1645027075.687"/>
<Point X="337" Y="127" T="1645027075.687"/>
<Point X="338" Y="127" T="1645027075.700"/>
<Point X="340" Y="126" T="1645027075.706"/>
<Point X="342" Y="125" T="1645027075.706"/>
<Point X="343" Y="125" T="1645027075.706"/>
<Point X="345" Y="124" T="1645027075.721"/>
<Point X="346" Y="124" T="1645027075.721"/>
<Point X="346" Y="123" T="1645027075.738"/>
<Point X="345" Y="123" T="1645027075.761"/>
<Point X="345" Y="122" T="1645027075.761"/>
<Point X="344" Y="122" T="1645027075.761"/>
<Point X="343" Y="122" T="1645027075.777"/>
<Point X="342" Y="122" T="1645027075.777"/>
<Point X="341" Y="122" T="1645027075.796"/>
<Point X="340" Y="123" T="1645027075.804"/>
<Point X="339" Y="123" T="1645027075.804"/>
<Point X="338" Y="122" T="1645027075.814"/>
<Point X="337" Y="122" T="1645027075.818"/>
<Point X="336" Y="122" T="1645027075.828"/>
<Point X="335" Y="122" T="1645027075.828"/>
<Point X="334" Y="122" T="1645027075.834"/>
<Point X="333" Y="122" T="1645027075.834"/>
<Point X="332" Y="122" T="1645027075.852"/>
<Point X="330" Y="121" T="1645027075.853"/>
<Point X="329" Y="121" T="1645027075.857"/>
<Point X="327" Y="121" T="1645027075.873"/>
<Point X="326" Y="121" T="1645027075.879"/>
<Point X="325" Y="121" T="1645027075.879"/>
<Point X="324" Y="120" T="1645027075.879"/>
<Point X="323" Y="120" T="1645027075.879"/>
<Point X="321" Y="120" T="1645027075.879"/>
<Point X="320" Y="120" T="1645027075.895"/>
<Point X="318" Y="120" T="1645027075.895"/>
<Point X="316" Y="120" T="1645027075.895"/>
<Point X="314" Y="120" T="1645027075.909"/>
<Point X="312" Y="120" T="1645027075.909"/>
<Point X="310" Y="120" T="1645027075.929"/>
<Point X="303" Y="120" T="1645027075.932"/>
<Point X="299" Y="121" T="1645027075.932"/>
<Point X="297" Y="121" T="1645027075.932"/>
<Point X="295" Y="121" T="1645027075.932"/>
<Point X="292" Y="121" T="1645027075.947"/>
<Point X="290" Y="122" T="1645027075.947"/>
<Point X="285" Y="122" T="1645027075.953"/>
<Point X="283" Y="123" T="1645027075.961"/>
<Point X="281" Y="123" T="1645027075.961"/>
<Point X="279" Y="123" T="1645027075.969"/>
<Point X="277" Y="123" T="1645027075.969"/>
<Point X="275" Y="123" T="1645027075.969"/>
<Point X="273" Y="123" T="1645027075.969"/>
<Point X="272" Y="123" T="1645027075.984"/>
<Point X="270" Y="123" T="1645027075.984"/>
<Point X="269" Y="123" T="1645027076.001"/>
<Point X="265" Y="123" T="1645027076.001"/>
<Point X="263" Y="123" T="1645027076.006"/>
<Point X="262" Y="123" T="1645027076.014"/>
<Point X="261" Y="123" T="1645027076.015"/>
<Point X="260" Y="123" T="1645027076.019"/>
<Point X="259" Y="123" T="1645027076.019"/>
<Point X="258" Y="123" T="1645027076.029"/>
<Point X="257" Y="123" T="1645027076.037"/>
<Point X="256" Y="123" T="1645027076.044"/>
<Point X="255" Y="123" T="1645027076.062"/>
<Point X="255" Y="122" T="1645027076.062"/>
<Point X="256" Y="122" T="1645027076.062"/>
<Point X="256" Y="121" T="1645027076.082"/>
<Point X="257" Y="121" T="1645027076.082"/>
<Point X="258" Y="121" T="1645027076.104"/>
<Point X="259" Y="120" T="1645027076.104"/>
<Point X="260" Y="120" T="1645027076.122"/>
<Point X="262" Y="120" T="1645027076.137"/>
<Point X="264" Y="120" T="1645027076.141"/>
<Point X="267" Y="120" T="1645027076.141"/>
<Point X="268" Y="119" T="1645027076.141"/>
<Point X="270" Y="119" T="1645027076.159"/>
<Point X="271" Y="119" T="1645027076.159"/>
<Point X="273" Y="119" T="1645027076.164"/>
<Point X="275" Y="118" T="1645027076.164"/>
<Point X="277" Y="118" T="1645027076.173"/>
<Point X="279" Y="118" T="1645027076.173"/>
<Point X="281" Y="118" T="1645027076.179"/>
<Point X="283" Y="118" T="1645027076.179"/>
<Point X="285" Y="118" T="1645027076.187"/>
<Point X="287" Y="118" T="1645027076.187"/>
<Point X="289" Y="118" T="1645027076.187"/>
<Point X="291" Y="118" T="1645027076.187"/>
<Point X="293" Y="118" T="1645027076.187"/>
<Point X="296" Y="118" T="1645027076.204"/>
<Point X="298" Y="118" T="1645027076.209"/>
<Point X="301" Y="118" T="1645027076.209"/>
<Point X="304" Y="118" T="1645027076.217"/>
<Point X="306" Y="118" T="1645027076.217"/>
<Point X="309" Y="118" T="1645027076.224"/>
<Point X="312" Y="118" T="1645027076.224"/>
<Point X="314" Y="118" T="1645027076.232"/>
<Point X="316" Y="118" T="1645027076.232"/>
<Point X="322" Y="118" T="1645027076.239"/>
<Point X="324" Y="117" T="1645027076.247"/>
<Point X="327" Y="117" T="1645027076.247"/>
<Point X="330" Y="117" T="1645027076.247"/>
<Point X="332" Y="116" T="1645027076.247"/>
<Point X="334" Y="116" T="1645027076.247"/>
<Point X="337" Y="116" T="1645027076.264"/>
<Point X="339" Y="115" T="1645027076.269"/>
<Point X="341" Y="115" T="1645027076.269"/>
<Point X="342" Y="114" T="1645027076.277"/>
<Point X="344" Y="114" T="1645027076.277"/>
<Point X="345" Y="114" T="1645027076.277"/>
<Point X="347" Y="114" T="1645027076.277"/>
<Point X="349" Y="114" T="1645027076.292"/>
<Point X="351" Y="113" T="1645027076.292"/>
<Point X="353" Y="113" T="1645027076.316"/>
<Point X="352" Y="114" T="1645027076.352"/>
<Point X="352" Y="115" T="1645027076.352"/>
<Point X="351" Y="115" T="1645027076.368"/>
<Point X="350" Y="115" T="1645027076.368"/>
<Point X="350" Y="116" T="1645027076.391"/>
<Point X="349" Y="116" T="1645027076.391"/>
<Point X="348" Y="116" T="1645027076.408"/>
<Point X="347" Y="117" T="1645027076.419"/>
<Point X="346" Y="117" T="1645027076.443"/>
<Point X="346" Y="118" T="1645027076.458"/>
<Point X="346" Y="119" T="1645027076.483"/>
<Point X="345" Y="119" T="1645027076.483"/>
<Point X="345" Y="120" T="1645027076.503"/>
<Point X="345" Y="121" T="1645027076.518"/>
<Point X="344" Y="121" T="1645027076.520"/>
<Point X="344" Y="123" T="1645027076.520"/>
<Point X="343" Y="125" T="1645027076.532"/>
<Point X="343" Y="126" T="1645027076.540"/>
<Point X="342" Y="127" T="1645027076.540"/>
<Point X="342" Y="128" T="1645027076.540"/>
<Point X="341" Y="130" T="1645027076.540"/>
<Point X="340" Y="131" T="1645027076.554"/>
<Point X="339" Y="133" T="1645027076.554"/>
<Point X="337" Y="135" T="1645027076.562"/>
<Point X="336" Y="137" T="1645027076.562"/>
<Point X="334" Y="139" T="1645027076.562"/>
<Point X="333" Y="141" T="1645027076.562"/>
<Point X="331" Y="143" T="1645027076.579"/>
<Point X="329" Y="146" T="1645027076.579"/>
<Point X="327" Y="148" T="1645027076.585"/>
<Point X="325" Y="151" T="1645027076.585"/>
<Point X="323" Y="153" T="1645027076.585"/>
<Point X="320" Y="156" T="1645027076.585"/>
<Point X="315" Y="161" T="1645027076.604"/>
<Point X="313" Y="163" T="1645027076.608"/>
<Point X="311" Y="165" T="1645027076.608"/>
<Point X="308" Y="169" T="1645027076.614"/>
<Point X="306" Y="171" T="1645027076.622"/>
<Point X="305" Y="172" T="1645027076.622"/>
<Point X="303" Y="174" T="1645027076.622"/>
<Point X="302" Y="176" T="1645027076.622"/>
<Point X="301" Y="177" T="1645027076.638"/>
<Point X="299" Y="179" T="1645027076.638"/>
<Point X="298" Y="181" T="1645027076.638"/>
<Point X="296" Y="182" T="1645027076.638"/>
<Point X="295" Y="184" T="1645027076.638"/>
<Point X="294" Y="185" T="1645027076.654"/>
<Point X="293" Y="187" T="1645027076.654"/>
<Point X="292" Y="188" T="1645027076.654"/>
<Point X="291" Y="189" T="1645027076.679"/>
<Point X="289" Y="192" T="1645027076.679"/>
</Gesture>
