<Gesture Name="left_square_brace04" User="0" Number="4" NumPts="108" Milliseconds="1393.805">
<Point X="275" Y="71" T="1645026979.000"/>
<Point X="259" Y="71" T="1645026979.524"/>
<Point X="257" Y="72" T="1645026979.536"/>
<Point X="256" Y="72" T="1645026979.536"/>
<Point X="254" Y="72" T="1645026979.544"/>
<Point X="253" Y="72" T="1645026979.544"/>
<Point X="252" Y="73" T="1645026979.551"/>
<Point X="250" Y="73" T="1645026979.551"/>
<Point X="249" Y="73" T="1645026979.551"/>
<Point X="247" Y="74" T="1645026979.551"/>
<Point X="246" Y="74" T="1645026979.570"/>
<Point X="244" Y="74" T="1645026979.570"/>
<Point X="241" Y="74" T="1645026979.570"/>
<Point X="240" Y="74" T="1645026979.570"/>
<Point X="239" Y="75" T="1645026979.570"/>
<Point X="236" Y="75" T="1645026979.587"/>
<Point X="235" Y="75" T="1645026979.587"/>
<Point X="234" Y="75" T="1645026979.587"/>
<Point X="233" Y="75" T="1645026979.606"/>
<Point X="232" Y="75" T="1645026979.607"/>
<Point X="231" Y="76" T="1645026979.611"/>
<Point X="230" Y="76" T="1645026979.620"/>
<Point X="229" Y="77" T="1645026979.620"/>
<Point X="228" Y="78" T="1645026979.634"/>
<Point X="228" Y="79" T="1645026979.642"/>
<Point X="228" Y="80" T="1645026979.642"/>
<Point X="227" Y="80" T="1645026979.664"/>
<Point X="227" Y="81" T="1645026979.672"/>
<Point X="227" Y="82" T="1645026979.687"/>
<Point X="227" Y="83" T="1645026979.700"/>
<Point X="228" Y="86" T="1645026979.732"/>
<Point X="228" Y="88" T="1645026979.749"/>
<Point X="229" Y="91" T="1645026979.762"/>
<Point X="229" Y="93" T="1645026979.762"/>
<Point X="230" Y="96" T="1645026979.785"/>
<Point X="230" Y="99" T="1645026979.785"/>
<Point X="231" Y="103" T="1645026979.801"/>
<Point X="232" Y="106" T="1645026979.806"/>
<Point X="233" Y="110" T="1645026979.814"/>
<Point X="233" Y="113" T="1645026979.823"/>
<Point X="234" Y="117" T="1645026979.829"/>
<Point X="234" Y="119" T="1645026979.831"/>
<Point X="234" Y="122" T="1645026979.838"/>
<Point X="234" Y="124" T="1645026979.838"/>
<Point X="234" Y="126" T="1645026979.838"/>
<Point X="234" Y="128" T="1645026979.838"/>
<Point X="234" Y="130" T="1645026979.838"/>
<Point X="234" Y="132" T="1645026979.859"/>
<Point X="234" Y="135" T="1645026979.859"/>
<Point X="235" Y="139" T="1645026979.859"/>
<Point X="235" Y="141" T="1645026979.875"/>
<Point X="235" Y="145" T="1645026979.875"/>
<Point X="236" Y="149" T="1645026979.875"/>
<Point X="236" Y="151" T="1645026979.892"/>
<Point X="236" Y="154" T="1645026979.893"/>
<Point X="237" Y="158" T="1645026979.893"/>
<Point X="237" Y="160" T="1645026979.911"/>
<Point X="237" Y="162" T="1645026979.911"/>
<Point X="237" Y="164" T="1645026979.920"/>
<Point X="237" Y="166" T="1645026979.920"/>
<Point X="237" Y="168" T="1645026979.920"/>
<Point X="237" Y="170" T="1645026979.920"/>
<Point X="237" Y="173" T="1645026979.920"/>
<Point X="237" Y="176" T="1645026979.942"/>
<Point X="237" Y="179" T="1645026979.950"/>
<Point X="237" Y="181" T="1645026979.958"/>
<Point X="238" Y="183" T="1645026979.964"/>
<Point X="239" Y="186" T="1645026979.971"/>
<Point X="240" Y="189" T="1645026979.990"/>
<Point X="240" Y="191" T="1645026980.001"/>
<Point X="241" Y="193" T="1645026980.012"/>
<Point X="241" Y="195" T="1645026980.024"/>
<Point X="241" Y="197" T="1645026980.077"/>
<Point X="241" Y="196" T="1645026980.154"/>
<Point X="242" Y="196" T="1645026980.206"/>
<Point X="243" Y="196" T="1645026980.245"/>
<Point X="244" Y="196" T="1645026980.248"/>
<Point X="245" Y="196" T="1645026980.248"/>
<Point X="246" Y="196" T="1645026980.265"/>
<Point X="247" Y="196" T="1645026980.265"/>
<Point X="248" Y="196" T="1645026980.265"/>
<Point X="249" Y="196" T="1645026980.279"/>
<Point X="250" Y="195" T="1645026980.279"/>
<Point X="252" Y="195" T="1645026980.288"/>
<Point X="253" Y="195" T="1645026980.288"/>
<Point X="255" Y="195" T="1645026980.295"/>
<Point X="257" Y="195" T="1645026980.296"/>
<Point X="258" Y="194" T="1645026980.296"/>
<Point X="260" Y="194" T="1645026980.296"/>
<Point X="262" Y="194" T="1645026980.296"/>
<Point X="264" Y="194" T="1645026980.311"/>
<Point X="266" Y="193" T="1645026980.316"/>
<Point X="268" Y="193" T="1645026980.316"/>
<Point X="270" Y="192" T="1645026980.320"/>
<Point X="272" Y="192" T="1645026980.320"/>
<Point X="275" Y="191" T="1645026980.332"/>
<Point X="277" Y="191" T="1645026980.332"/>
<Point X="279" Y="190" T="1645026980.340"/>
<Point X="281" Y="190" T="1645026980.340"/>
<Point X="283" Y="190" T="1645026980.347"/>
<Point X="285" Y="189" T="1645026980.347"/>
<Point X="287" Y="189" T="1645026980.355"/>
<Point X="289" Y="189" T="1645026980.357"/>
<Point X="290" Y="189" T="1645026980.361"/>
<Point X="292" Y="189" T="1645026980.361"/>
<Point X="295" Y="189" T="1645026980.370"/>
<Point X="297" Y="190" T="1645026980.376"/>
<Point X="299" Y="191" T="1645026980.394"/>
</Gesture>
